django_forms_test.py
django_forms_test-0.1.post1.dist-info/DESCRIPTION.rst
django_forms_test-0.1.post1.dist-info/METADATA
django_forms_test-0.1.post1.dist-info/RECORD
django_forms_test-0.1.post1.dist-info/WHEEL
django_forms_test-0.1.post1.dist-info/metadata.json
django_forms_test-0.1.post1.dist-info/top_level.txt
