Metadata-Version: 2.0
Name: django-forms-test
Version: 0.1.post1
Summary: Module to simplify testing forms in Django framework
Home-page: https://github.com/Thyrst/django-forms-test
Author: Thyrst
Author-email: thyrst@seznam.cz
License: MIT
Download-URL: https://github.com/Thyrst/django-forms-test/archive/0.1.post1.tar.gz
Keywords: django forms unittest test
Platform: UNKNOWN
Classifier: Development Status :: 5 - Production/Stable
Classifier: Intended Audience :: Developers
Classifier: License :: OSI Approved :: MIT License
Classifier: Natural Language :: English
Classifier: Topic :: Software Development :: Libraries :: Python Modules
Classifier: Programming Language :: Python :: 3.6
